MANIFEST.in
README.md
setup.py
kog_lib/__init__.py
kog_lib.egg-info/PKG-INFO
kog_lib.egg-info/SOURCES.txt
kog_lib.egg-info/dependency_links.txt
kog_lib.egg-info/requires.txt
kog_lib.egg-info/top_level.txt
kog_lib/excel/__init__.py
kog_lib/excel/sf_csv.py
kog_lib/excel/sf_excel.py
kog_lib/filesystem/__init__.py
kog_lib/filesystem/sf_filesystem.py
kog_lib/mail/__init__.py
kog_lib/mail/sf_mail.py
kog_lib/metadata/__init__.py
kog_lib/metadata/sf_metadata.py
kog_lib/textgrid/__init__.py
kog_lib/textgrid/sf_textgrid.py
kog_lib/utils/__init__.py
kog_lib/utils/sf_utils.py
kog_lib/wav/__init__.py
kog_lib/wav/sf_wav.py