Metadata-Version: 2.1
Name: kog-lib
Version: 0.2.3
Summary: Simple python lib, processing excel,mail,textgrid,metadata,wav; using for SurfingTech or others
Home-page: UNKNOWN
Author: KOG
Author-email: 52204413@qq.com
License: BSD License
Platform: all
Classifier: Development Status :: 4 - Beta
Classifier: Operating System :: OS Independent
Classifier: Intended Audience :: Developers
Classifier: License :: OSI Approved :: BSD License
Classifier: Programming Language :: Python :: 3
Classifier: Programming Language :: Python :: 3.6
Classifier: Programming Language :: Python :: 3.7
Classifier: Topic :: Software Development :: Libraries
